{"expectation":"[{ type: 'function', name: 'invoke', payload: [2], meta: { instanceId: 1, invokeId: 1 } }, { type: 'callback', name: 'invoke', payload: [null, 3], meta: { sourceType: 'function', sourceInstanceId: 1, sourceInvokeId: 1, sourcePath: [1] } }, { type: 'function', name: 'return', meta: { instanceId: 1, invokeId: 1 } }]","actions":[{"type":"function","name":"construct","meta":{"functionName":"success"},"instanceId":1},{"type":"function","name":"invoke","payload":[2,null],"instanceId":1,"invokeId":1},{"type":"callback","name":"invoke","payload":[null,3],"sourceType":"function","sourceInstanceId":1,"sourceInvokeId":1,"sourcePath":[1]}]}
