{"expectation":"[{ type: 'class/constructor', payload: [] }, { type: 'class/invoke', payload: [3], meta: { name: 'increment' } }, { type: 'class/return', payload: {}, meta: { returnType: 'promise' } }, { type: 'promise', payload: 4, meta: { status: 'resolve' } }]","actions":[{"type":"class/constructor","payload":[]},{"type":"class/invoke","payload":[3],"meta":{"methodId":0,"name":"increment"}},{"type":"class/return","payload":{},"meta":{"methodId":0,"returnType":"promise","promiseId":2}},{"type":"promise","meta":{"promiseId":2,"status":"resolve"},"payload":4}]}