{"expectation":"[{ type: 'class', name: 'construct', payload: [], meta: { className: 'WithCallback' }, instanceId: 1 }, { type: 'class', name: 'invoke', payload: [1], meta: { methodName: 'justDo' }, instanceId: 1, invokeId: 1 }, { type: 'class', name: 'return', payload: 1, meta: { methodName: 'justDo' }, instanceId: 1, invokeId: 1 }, { type: 'class', name: 'invoke', payload: [], meta: { methodName: 'callback' }, instanceId: 1, invokeId: 2 }, { type: 'class', name: 'return', meta: { methodName: 'callback' }, instanceId: 1, invokeId: 2 }, { type: 'class', name: 'invoke', payload: [], meta: { methodName: 'callback' }, instanceId: 1, invokeId: 3 }, { type: 'class', name: 'return', meta: { methodName: 'callback' }, instanceId: 1, invokeId: 3 }, { type: 'callback', name: 'invoke', payload: ['called'], sourceType: 'class', sourceInstanceId: 1, sourceInvokeId: 2, sourcePath: [0] }, { type: 'callback', name: 'invoke', payload: ['called'], sourceType: 'class', sourceInstanceId: 1, sourceInvokeId: 3, sourcePath: [0] }]","actions":[{"type":"class","name":"construct","payload":[],"meta":{"className":"WithCallback"},"instanceId":1},{"type":"class","name":"invoke","payload":[1],"meta":{"methodName":"justDo"},"invokeId":1,"instanceId":1},{"type":"class","name":"return","payload":1,"meta":{"methodName":"justDo"},"invokeId":1,"instanceId":1},{"type":"class","name":"invoke","payload":[null],"meta":{"methodName":"callback"},"invokeId":2,"instanceId":1},{"type":"class","name":"return","meta":{"methodName":"callback"},"invokeId":2,"instanceId":1},{"type":"class","name":"invoke","payload":[null],"meta":{"methodName":"callback"},"invokeId":3,"instanceId":1},{"type":"class","name":"return","meta":{"methodName":"callback"},"invokeId":3,"instanceId":1},{"type":"callback","name":"invoke","sourceType":"class","payload":["called"],"sourceInvokeId":2,"sourcePath":[0],"sourceInstanceId":1},{"type":"callback","name":"invoke","sourceType":"class","payload":["called"],"sourceInvokeId":3,"sourcePath":[0],"sourceInstanceId":1}]}