{"expectation":"[{ type: 'function', name: 'construct', meta: { functionName: 'fail' }, instanceId: 1 }, { type: 'function', name: 'invoke', payload: ['increment', 2], invokeId: 1, instanceId: 1 }, { type: 'function', name: 'return', payload: {}, invokeId: 1, returnType: 'promise', returnInstanceId: 1, instanceId: 1 }, { type: 'promise', name: 'construct', instanceId: 1 }, { type: 'promise', name: 'return', payload: { message: 'fail' }, meta: { state: 'rejected' }, invokeId: 1, instanceId: 1 }]","actions":[{"type":"function","name":"construct","meta":{"functionName":"fail"},"instanceId":1},{"type":"function","name":"invoke","payload":["increment",2],"invokeId":1,"instanceId":1},{"type":"function","name":"return","payload":{},"invokeId":1,"instanceId":1,"returnType":"promise","returnInstanceId":1},{"type":"promise","name":"construct","instanceId":1},{"type":"promise","name":"return","payload":{"message":"fail"},"meta":{"state":"rejected"},"invokeId":1,"instanceId":1}]}